[[1.315609,{"lines":{"0":[["                                                                                ",{}]],"1":[["                                                                                ",{}]],"2":[["                                                                                ",{}]],"3":[["                                                                                ",{}]],"4":[["                                                                                ",{}]],"5":[["                                                                                ",{}]],"6":[["                                                                                ",{}]],"7":[["                                                                                ",{}]],"8":[["                                                                                ",{}]],"9":[["                                                                                ",{}]],"10":[["                                                                                ",{}]],"11":[["                                                                                ",{}]],"12":[["                                                                                ",{}]],"13":[["                                                                                ",{}]],"14":[["                                                                                ",{}]],"15":[["                                                                                ",{}]],"16":[["                                                                                ",{}]],"17":[["                                                                                ",{}]],"18":[["                                                                                ",{}]],"19":[["                                                                                ",{}]],"20":[["                                                                                ",{}]],"21":[["                                                                                ",{}]],"22":[["                                                                                ",{}]]},"cursor":{"x":0,"y":0,"visible":true}}],[0.017834,{"lines":{"0":[["➜ ",{"fg":1,"bold":true}],[" ",{"fg":2,"bold":true}],["~ ",{"fg":6,"bold":true}],[" ",{"fg":4,"bold":true}],["                                                                          ",{}]]},"cursor":{"x":6}}],[27.643007,{"lines":{"0":[["➜ ",{"fg":1,"bold":true}],[" ",{"fg":2,"bold":true}],["~ ",{"fg":6,"bold":true}],[" ",{"fg":4,"bold":true}],["C                                                                         ",{}]]},"cursor":{"x":7}}],[0.243007,{"lines":{"0":[["➜ ",{"fg":1,"bold":true}],[" ",{"fg":2,"bold":true}],["~ ",{"fg":6,"bold":true}],[" ",{"fg":4,"bold":true}],["Ci                                                                        ",{}]]},"cursor":{"x":8}}],[0.207977,{"lines":{"0":[["➜ ",{"fg":1,"bold":true}],[" ",{"fg":2,"bold":true}],["~ ",{"fg":6,"bold":true}],[" ",{"fg":4,"bold":true}],["Cih                                                                       ",{}]]},"cursor":{"x":9}}],[0.199977,{"lines":{"0":[["➜ ",{"fg":1,"bold":true}],[" ",{"fg":2,"bold":true}],["~ ",{"fg":6,"bold":true}],[" ",{"fg":4,"bold":true}],["Ciha                                                                      ",{}]]},"cursor":{"x":10}}],[0.128203,{"lines":{"0":[["➜ ",{"fg":1,"bold":true}],[" ",{"fg":2,"bold":true}],["~ ",{"fg":6,"bold":true}],[" ",{"fg":4,"bold":true}],["Cihan                                                                     ",{}]]},"cursor":{"x":11}}],[0.111659,{"lines":{"0":[["➜ ",{"fg":1,"bold":true}],[" ",{"fg":2,"bold":true}],["~ ",{"fg":6,"bold":true}],[" ",{"fg":4,"bold":true}],["Cihang                                                                    ",{}]]},"cursor":{"x":12}}],[0.088176,{"lines":{"0":[["➜ ",{"fg":1,"bold":true}],[" ",{"fg":2,"bold":true}],["~ ",{"fg":6,"bold":true}],[" ",{"fg":4,"bold":true}],["Cihangi                                                                   ",{}]]},"cursor":{"x":13}}],[0.096093,{"lines":{"0":[["➜ ",{"fg":1,"bold":true}],[" ",{"fg":2,"bold":true}],["~ ",{"fg":6,"bold":true}],[" ",{"fg":4,"bold":true}],["Cihangir                                                                  ",{}]]},"cursor":{"x":14}}],[0.07978399999999999,{"cursor":{"x":15}}],[2.31999,{"cursor":{"x":14}}],[0.128036,{"lines":{"0":[["➜ ",{"fg":1,"bold":true}],[" ",{"fg":2,"bold":true}],["~ ",{"fg":6,"bold":true}],[" ",{"fg":4,"bold":true}],["Cihangi                                                                   ",{}]]},"cursor":{"x":13}}],[0.135796,{"lines":{"0":[["➜ ",{"fg":1,"bold":true}],[" ",{"fg":2,"bold":true}],["~ ",{"fg":6,"bold":true}],[" ",{"fg":4,"bold":true}],["Cihang                                                                    ",{}]]},"cursor":{"x":12}}],[0.144011,{"lines":{"0":[["➜ ",{"fg":1,"bold":true}],[" ",{"fg":2,"bold":true}],["~ ",{"fg":6,"bold":true}],[" ",{"fg":4,"bold":true}],["Cihan                                                                     ",{}]]},"cursor":{"x":11}}],[0.136073,{"lines":{"0":[["➜ ",{"fg":1,"bold":true}],[" ",{"fg":2,"bold":true}],["~ ",{"fg":6,"bold":true}],[" ",{"fg":4,"bold":true}],["Ciha                                                                      ",{}]]},"cursor":{"x":10}}],[0.135935,{"lines":{"0":[["➜ ",{"fg":1,"bold":true}],[" ",{"fg":2,"bold":true}],["~ ",{"fg":6,"bold":true}],[" ",{"fg":4,"bold":true}],["Cih                                                                       ",{}]]},"cursor":{"x":9}}],[0.144037,{"lines":{"0":[["➜ ",{"fg":1,"bold":true}],[" ",{"fg":2,"bold":true}],["~ ",{"fg":6,"bold":true}],[" ",{"fg":4,"bold":true}],["Ci                                                                        ",{}]]},"cursor":{"x":8}}],[0.160066,{"lines":{"0":[["➜ ",{"fg":1,"bold":true}],[" ",{"fg":2,"bold":true}],["~ ",{"fg":6,"bold":true}],[" ",{"fg":4,"bold":true}],["C                                                                         ",{}]]},"cursor":{"x":7}}],[0.135891,{"lines":{"0":[["➜ ",{"fg":1,"bold":true}],[" ",{"fg":2,"bold":true}],["~ ",{"fg":6,"bold":true}],[" ",{"fg":4,"bold":true}],["                                                                          ",{}]]},"cursor":{"x":6}}],[41.231319,{"lines":{"0":[["➜ ",{"fg":1,"bold":true}],[" ",{"fg":2,"bold":true}],["~ ",{"fg":6,"bold":true}],[" ",{"fg":4,"bold":true}],["e                                                                         ",{}]]},"cursor":{"x":7}}],[0.767631,{"lines":{"0":[["➜ ",{"fg":1,"bold":true}],[" ",{"fg":2,"bold":true}],["~ ",{"fg":6,"bold":true}],[" ",{"fg":4,"bold":true}],["                                                                          ",{}]]},"cursor":{"x":6}}],[1.880023,{"lines":{"0":[["➜ ",{"fg":1,"bold":true}],[" ",{"fg":2,"bold":true}],["~ ",{"fg":6,"bold":true}],[" ",{"fg":4,"bold":true}],["r                                                                         ",{}]]},"cursor":{"x":7}}],[0.09599000000000001,{"lines":{"0":[["➜ ",{"fg":1,"bold":true}],[" ",{"fg":2,"bold":true}],["~ ",{"fg":6,"bold":true}],[" ",{"fg":4,"bold":true}],["ra                                                                        ",{}]]},"cursor":{"x":8}}],[0.111826,{"lines":{"0":[["➜ ",{"fg":1,"bold":true}],[" ",{"fg":2,"bold":true}],["~ ",{"fg":6,"bold":true}],[" ",{"fg":4,"bold":true}],["ras                                                                       ",{}]]},"cursor":{"x":9}}],[0.200184,{"lines":{"0":[["➜ ",{"fg":1,"bold":true}],[" ",{"fg":2,"bold":true}],["~ ",{"fg":6,"bold":true}],[" ",{"fg":4,"bold":true}],["rast                                                                      ",{}]]},"cursor":{"x":10}}],[0.087792,{"lines":{"0":[["➜ ",{"fg":1,"bold":true}],[" ",{"fg":2,"bold":true}],["~ ",{"fg":6,"bold":true}],[" ",{"fg":4,"bold":true}],["rasta                                                                     ",{}]]},"cursor":{"x":11}}],[0.127929,{"cursor":{"x":12}}],[0.088089,{"lines":{"0":[["➜ ",{"fg":1,"bold":true}],[" ",{"fg":2,"bold":true}],["~ ",{"fg":6,"bold":true}],[" ",{"fg":4,"bold":true}],["rasta b                                                                   ",{}]]},"cursor":{"x":13}}],[0.152156,{"lines":{"0":[["➜ ",{"fg":1,"bold":true}],[" ",{"fg":2,"bold":true}],["~ ",{"fg":6,"bold":true}],[" ",{"fg":4,"bold":true}],["rasta ba                                                                  ",{}]]},"cursor":{"x":14}}],[0.152093,{"lines":{"0":[["➜ ",{"fg":1,"bold":true}],[" ",{"fg":2,"bold":true}],["~ ",{"fg":6,"bold":true}],[" ",{"fg":4,"bold":true}],["rasta bab                                                                 ",{}]]},"cursor":{"x":15}}],[0.17599,{"lines":{"0":[["➜ ",{"fg":1,"bold":true}],[" ",{"fg":2,"bold":true}],["~ ",{"fg":6,"bold":true}],[" ",{"fg":4,"bold":true}],["rasta baba                                                                ",{}]]},"cursor":{"x":16}}],[0.184331,{"lines":{"0":[["➜ ",{"fg":1,"bold":true}],[" ",{"fg":2,"bold":true}],["~ ",{"fg":6,"bold":true}],[" ",{"fg":4,"bold":true}],["rasta babay                                                               ",{}]]},"cursor":{"x":17}}],[0.119706,{"lines":{"0":[["➜ ",{"fg":1,"bold":true}],[" ",{"fg":2,"bold":true}],["~ ",{"fg":6,"bold":true}],[" ",{"fg":4,"bold":true}],["rasta babayi                                                              ",{}]]},"cursor":{"x":18}}],[0.127791,{"cursor":{"x":19}}],[0.128112,{"lines":{"0":[["➜ ",{"fg":1,"bold":true}],[" ",{"fg":2,"bold":true}],["~ ",{"fg":6,"bold":true}],[" ",{"fg":4,"bold":true}],["rasta babayi k                                                            ",{}]]},"cursor":{"x":20}}],[0.183935,{"lines":{"0":[["➜ ",{"fg":1,"bold":true}],[" ",{"fg":2,"bold":true}],["~ ",{"fg":6,"bold":true}],[" ",{"fg":4,"bold":true}],["rasta babayi ko                                                           ",{}]]},"cursor":{"x":21}}],[0.176032,{"lines":{"0":[["➜ ",{"fg":1,"bold":true}],[" ",{"fg":2,"bold":true}],["~ ",{"fg":6,"bold":true}],[" ",{"fg":4,"bold":true}],["rasta babayi kop                                                          ",{}]]},"cursor":{"x":22}}],[0.167977,{"lines":{"0":[["➜ ",{"fg":1,"bold":true}],[" ",{"fg":2,"bold":true}],["~ ",{"fg":6,"bold":true}],[" ",{"fg":4,"bold":true}],["rasta babayi kopa                                                         ",{}]]},"cursor":{"x":23}}],[0.081105,{"lines":{"0":[["➜ ",{"fg":1,"bold":true}],[" ",{"fg":2,"bold":true}],["~ ",{"fg":6,"bold":true}],[" ",{"fg":4,"bold":true}],["rasta babayi kopar                                                        ",{}]]},"cursor":{"x":24}}],[0.174865,{"lines":{"0":[["➜ ",{"fg":1,"bold":true}],[" ",{"fg":2,"bold":true}],["~ ",{"fg":6,"bold":true}],[" ",{"fg":4,"bold":true}],["rasta babayi kopart                                                       ",{}]]},"cursor":{"x":25}}],[0.103886,{"lines":{"0":[["➜ ",{"fg":1,"bold":true}],[" ",{"fg":2,"bold":true}],["~ ",{"fg":6,"bold":true}],[" ",{"fg":4,"bold":true}],["rasta babayi kopartm                                                      ",{}]]},"cursor":{"x":26}}],[0.064141,{"lines":{"0":[["➜ ",{"fg":1,"bold":true}],[" ",{"fg":2,"bold":true}],["~ ",{"fg":6,"bold":true}],[" ",{"fg":4,"bold":true}],["rasta babayi kopartmi                                                     ",{}]]},"cursor":{"x":27}}],[0.12798,{"lines":{"0":[["➜ ",{"fg":1,"bold":true}],[" ",{"fg":2,"bold":true}],["~ ",{"fg":6,"bold":true}],[" ",{"fg":4,"bold":true}],["rasta babayi kopartmis                                                    ",{}]]},"cursor":{"x":28}}],[0.216108,{"lines":{"0":[["➜ ",{"fg":1,"bold":true}],[" ",{"fg":2,"bold":true}],["~ ",{"fg":6,"bold":true}],[" ",{"fg":4,"bold":true}],["rasta babayi kopartmisl                                                   ",{}]]},"cursor":{"x":29}}],[0.319902,{"lines":{"0":[["➜ ",{"fg":1,"bold":true}],[" ",{"fg":2,"bold":true}],["~ ",{"fg":6,"bold":true}],[" ",{"fg":4,"bold":true}],["rasta babayi kopartmisla                                                  ",{}]]},"cursor":{"x":30}}],[0.06395199999999999,{"lines":{"0":[["➜ ",{"fg":1,"bold":true}],[" ",{"fg":2,"bold":true}],["~ ",{"fg":6,"bold":true}],[" ",{"fg":4,"bold":true}],["rasta babayi kopartmislar                                                 ",{}]]},"cursor":{"x":31}}],[0.608158,{"cursor":{"x":32}}],[0.175716,{"lines":{"0":[["➜ ",{"fg":1,"bold":true}],[" ",{"fg":2,"bold":true}],["~ ",{"fg":6,"bold":true}],[" ",{"fg":4,"bold":true}],["rasta babayi kopartmislar 1                                               ",{}]]},"cursor":{"x":33}}],[0.09614200000000001,{"lines":{"0":[["➜ ",{"fg":1,"bold":true}],[" ",{"fg":2,"bold":true}],["~ ",{"fg":6,"bold":true}],[" ",{"fg":4,"bold":true}],["rasta babayi kopartmislar 10                                              ",{}]]},"cursor":{"x":34}}],[0.183887,{"cursor":{"x":35}}],[0.064045,{"lines":{"0":[["➜ ",{"fg":1,"bold":true}],[" ",{"fg":2,"bold":true}],["~ ",{"fg":6,"bold":true}],[" ",{"fg":4,"bold":true}],["rasta babayi kopartmislar 10 a                                            ",{}]]},"cursor":{"x":36}}],[0.095878,{"lines":{"0":[["➜ ",{"fg":1,"bold":true}],[" ",{"fg":2,"bold":true}],["~ ",{"fg":6,"bold":true}],[" ",{"fg":4,"bold":true}],["rasta babayi kopartmislar 10 ad                                           ",{}]]},"cursor":{"x":37}}],[0.096202,{"lines":{"0":[["➜ ",{"fg":1,"bold":true}],[" ",{"fg":2,"bold":true}],["~ ",{"fg":6,"bold":true}],[" ",{"fg":4,"bold":true}],["rasta babayi kopartmislar 10 ada                                          ",{}]]},"cursor":{"x":38}}],[0.103973,{"lines":{"0":[["➜ ",{"fg":1,"bold":true}],[" ",{"fg":2,"bold":true}],["~ ",{"fg":6,"bold":true}],[" ",{"fg":4,"bold":true}],["rasta babayi kopartmislar 10 adam                                         ",{}]]},"cursor":{"x":39}}],[0.672021,{"cursor":{"x":40}}],[0.095818,{"lines":{"0":[["➜ ",{"fg":1,"bold":true}],[" ",{"fg":2,"bold":true}],["~ ",{"fg":6,"bold":true}],[" ",{"fg":4,"bold":true}],["rasta babayi kopartmislar 10 adam e                                       ",{}]]},"cursor":{"x":41}}],[0.160136,{"lines":{"0":[["➜ ",{"fg":1,"bold":true}],[" ",{"fg":2,"bold":true}],["~ ",{"fg":6,"bold":true}],[" ",{"fg":4,"bold":true}],["rasta babayi kopartmislar 10 adam ev                                      ",{}]]},"cursor":{"x":42}}],[0.07198499999999999,{"lines":{"0":[["➜ ",{"fg":1,"bold":true}],[" ",{"fg":2,"bold":true}],["~ ",{"fg":6,"bold":true}],[" ",{"fg":4,"bold":true}],["rasta babayi kopartmislar 10 adam evi                                     ",{}]]},"cursor":{"x":43}}],[0.079981,{"lines":{"0":[["➜ ",{"fg":1,"bold":true}],[" ",{"fg":2,"bold":true}],["~ ",{"fg":6,"bold":true}],[" ",{"fg":4,"bold":true}],["rasta babayi kopartmislar 10 adam evin                                    ",{}]]},"cursor":{"x":44}}],[0.080209,{"lines":{"0":[["➜ ",{"fg":1,"bold":true}],[" ",{"fg":2,"bold":true}],["~ ",{"fg":6,"bold":true}],[" ",{"fg":4,"bold":true}],["rasta babayi kopartmislar 10 adam evini                                   ",{}]]},"cursor":{"x":45}}],[0.159719,{"cursor":{"x":46}}],[0.08007499999999999,{"lines":{"0":[["➜ ",{"fg":1,"bold":true}],[" ",{"fg":2,"bold":true}],["~ ",{"fg":6,"bold":true}],[" ",{"fg":4,"bold":true}],["rasta babayi kopartmislar 10 adam evini b                                 ",{}]]},"cursor":{"x":47}}],[0.19199,{"lines":{"0":[["➜ ",{"fg":1,"bold":true}],[" ",{"fg":2,"bold":true}],["~ ",{"fg":6,"bold":true}],[" ",{"fg":4,"bold":true}],["rasta babayi kopartmislar 10 adam evini ba                                ",{}]]},"cursor":{"x":48}}],[0.08005,{"lines":{"0":[["➜ ",{"fg":1,"bold":true}],[" ",{"fg":2,"bold":true}],["~ ",{"fg":6,"bold":true}],[" ",{"fg":4,"bold":true}],["rasta babayi kopartmislar 10 adam evini bas                               ",{}]]},"cursor":{"x":49}}],[0.623937,{"lines":{"0":[["➜ ",{"fg":1,"bold":true}],[" ",{"fg":2,"bold":true}],["~ ",{"fg":6,"bold":true}],[" ",{"fg":4,"bold":true}],["rasta babayi kopartmislar 10 adam evini basm                              ",{}]]},"cursor":{"x":50}}],[0.048112,{"lines":{"0":[["➜ ",{"fg":1,"bold":true}],[" ",{"fg":2,"bold":true}],["~ ",{"fg":6,"bold":true}],[" ",{"fg":4,"bold":true}],["rasta babayi kopartmislar 10 adam evini basmi                             ",{}]]},"cursor":{"x":51}}],[0.151874,{"lines":{"0":[["➜ ",{"fg":1,"bold":true}],[" ",{"fg":2,"bold":true}],["~ ",{"fg":6,"bold":true}],[" ",{"fg":4,"bold":true}],["rasta babayi kopartmislar 10 adam evini basmis                            ",{}]]},"cursor":{"x":52}}],[0.103779,{"lines":{"0":[["➜ ",{"fg":1,"bold":true}],[" ",{"fg":2,"bold":true}],["~ ",{"fg":6,"bold":true}],[" ",{"fg":4,"bold":true}],["rasta babayi kopartmislar 10 adam evini basmisl                           ",{}]]},"cursor":{"x":53}}],[0.09624099999999999,{"lines":{"0":[["➜ ",{"fg":1,"bold":true}],[" ",{"fg":2,"bold":true}],["~ ",{"fg":6,"bold":true}],[" ",{"fg":4,"bold":true}],["rasta babayi kopartmislar 10 adam evini basmisla                          ",{}]]},"cursor":{"x":54}}],[0.047961,{"lines":{"0":[["➜ ",{"fg":1,"bold":true}],[" ",{"fg":2,"bold":true}],["~ ",{"fg":6,"bold":true}],[" ",{"fg":4,"bold":true}],["rasta babayi kopartmislar 10 adam evini basmislar                         ",{}]]},"cursor":{"x":55}}],[1.192022,{"cursor":{"x":0,"y":1}}],[0.102744,{"lines":{"1":[["zsh: correct 'rasta' to 'asa' [nyae]?                                           ",{}]]},"cursor":{"x":38}}],[1.912826,{"lines":{"1":[["zsh: correct 'rasta' to 'asa' [nyae]? n                                         ",{}]]},"cursor":{"x":0,"y":2}}],[0.001473,{}],[0.018869,{"lines":{"2":[["zsh: command not found: rasta                                                   ",{}]]},"cursor":{"y":3}}],[0.008501,{"lines":{"3":[["➜ ",{"fg":1,"bold":true}],[" ",{"fg":2,"bold":true}],["~ ",{"fg":6,"bold":true}],[" ",{"fg":4,"bold":true}],["                                                                          ",{}]]},"cursor":{"x":6}}],[4.043529,{"cursor":{"x":0,"y":4}}]]