[[1.492932,{"lines":{"0":[["                                                                                ",{}]],"1":[["                                                                                ",{}]],"2":[["                                                                                ",{}]],"3":[["                                                                                ",{}]],"4":[["                                                                                ",{}]],"5":[["                                                                                ",{}]],"6":[["                                                                                ",{}]],"7":[["                                                                                ",{}]],"8":[["                                                                                ",{}]],"9":[["                                                                                ",{}]],"10":[["                                                                                ",{}]],"11":[["                                                                                ",{}]],"12":[["                                                                                ",{}]],"13":[["                                                                                ",{}]],"14":[["                                                                                ",{}]],"15":[["                                                                                ",{}]],"16":[["                                                                                ",{}]],"17":[["                                                                                ",{}]],"18":[["                                                                                ",{}]],"19":[["                                                                                ",{}]],"20":[["                                                                                ",{}]],"21":[["                                                                                ",{}]],"22":[["                                                                                ",{}]],"23":[["                                                                                ",{}]]},"cursor":{"x":0,"y":0,"visible":true}}],[0.002855,{}],[0.027082,{"lines":{"0":[["[oneadmin@ovz01 conf]$                                                          ",{}]]},"cursor":{"x":23}}],[19.094108,{"lines":{"0":[["[oneadmin@ovz01 conf]$ s                                                        ",{}]]},"cursor":{"x":24}}],[0.082009,{"lines":{"0":[["[oneadmin@ovz01 conf]$ su                                                       ",{}]]},"cursor":{"x":25}}],[0.143886,{"lines":{"0":[["[oneadmin@ovz01 conf]$ sud                                                      ",{}]]},"cursor":{"x":26}}],[0.053881,{"lines":{"0":[["[oneadmin@ovz01 conf]$ sudo                                                     ",{}]]},"cursor":{"x":27}}],[0.044141,{"cursor":{"x":28}}],[5.957981,{"lines":{"0":[["[oneadmin@ovz01 conf]$ sudo v                                                   ",{}]]},"cursor":{"x":29}}],[0.114053,{"lines":{"0":[["[oneadmin@ovz01 conf]$ sudo vz                                                  ",{}]]},"cursor":{"x":30}}],[0.266823,{"lines":{"0":[["[oneadmin@ovz01 conf]$ sudo vzc                                                 ",{}]]},"cursor":{"x":31}}],[0.34115,{"lines":{"0":[["[oneadmin@ovz01 conf]$ sudo vzct                                                ",{}]]},"cursor":{"x":32}}],[0.267249,{"lines":{"0":[["[oneadmin@ovz01 conf]$ sudo vzctl                                               ",{}]]},"cursor":{"x":33}}],[0.118934,{"cursor":{"x":34}}],[0.567807,{"lines":{"0":[["[oneadmin@ovz01 conf]$ sudo vzctl s                                             ",{}]]},"cursor":{"x":35}}],[0.613157,{"lines":{"0":[["[oneadmin@ovz01 conf]$ sudo vzctl st                                            ",{}]]},"cursor":{"x":36}}],[0.149691,{"lines":{"0":[["[oneadmin@ovz01 conf]$ sudo vzctl star                                          ",{}]]},"cursor":{"x":38}}],[0.115321,{"lines":{"0":[["[oneadmin@ovz01 conf]$ sudo vzctl start                                         ",{}]]},"cursor":{"x":40}}],[0.651797,{"lines":{"0":[["[oneadmin@ovz01 conf]$ sudo vzctl start 10                                      ",{}]]},"cursor":{"x":42}}],[0.18007,{"lines":{"0":[["[oneadmin@ovz01 conf]$ sudo vzctl start 105                                     ",{}]]},"cursor":{"x":43}}],[0.25101,{"cursor":{"x":0,"y":1}}],[0.312934,{"lines":{"1":[["Starting container ...                                                          ",{}]],"2":[["Container is mounted                                                            ",{}]]},"cursor":{"y":3}}],[0.040007,{"lines":{"3":[["Adding IP address(es): 192.168.1.105                                            ",{}]]},"cursor":{"y":4}}],[6.766201,{"lines":{"4":[["Setting CPU units: 1000                                                         ",{}]]},"cursor":{"y":5}}],[0.724919,{"lines":{"5":[["Container start in progress...                                                  ",{}]]},"cursor":{"y":6}}],[0.080124,{"lines":{"6":[["[oneadmin@ovz01 conf]$                                                          ",{}]]},"cursor":{"x":23}}],[3.298752,{"lines":{"6":[["[oneadmin@ovz01 conf]$ sudo vzctl start 105                                     ",{}]]},"cursor":{"x":43}}],[1.582934,{"lines":{"6":[["[oneadmin@ovz01 conf]$ sudo vzctl start 10                                      ",{}]]},"cursor":{"x":42}}],[0.200244,{"lines":{"6":[["[oneadmin@ovz01 conf]$ sudo vzctl start 1                                       ",{}]]},"cursor":{"x":41}}],[0.182099,{"lines":{"6":[["[oneadmin@ovz01 conf]$ sudo vzctl start                                         ",{}]]},"cursor":{"x":40}}],[0.674946,{"lines":{"6":[["[oneadmin@ovz01 conf]$ sudo vzctl start s                                       ",{}]]},"cursor":{"x":41}}],[0.164986,{"lines":{"6":[["[oneadmin@ovz01 conf]$ sudo vzctl start se                                      ",{}]]},"cursor":{"x":42}}],[0.17598,{"lines":{"6":[["[oneadmin@ovz01 conf]$ sudo vzctl start ser                                     ",{}]]},"cursor":{"x":43}}],[0.221134,{"lines":{"6":[["[oneadmin@ovz01 conf]$ sudo vzctl start serv                                    ",{}]]},"cursor":{"x":44}}],[0.106899,{"lines":{"6":[["[oneadmin@ovz01 conf]$ sudo vzctl start servi                                   ",{}]]},"cursor":{"x":45}}],[0.103609,{"lines":{"6":[["[oneadmin@ovz01 conf]$ sudo vzctl start servic                                  ",{}]]},"cursor":{"x":46}}],[0.071225,{"lines":{"6":[["[oneadmin@ovz01 conf]$ sudo vzctl start service                                 ",{}]]},"cursor":{"x":47}}],[0.184905,{"cursor":{"x":48}}],[0.665801,{"lines":{"6":[["[oneadmin@ovz01 conf]$ sudo vzctl start service s                               ",{}]]},"cursor":{"x":49}}],[0.13226,{"lines":{"6":[["[oneadmin@ovz01 conf]$ sudo vzctl start service ss                              ",{}]]},"cursor":{"x":50}}],[0.586794,{"lines":{"6":[["[oneadmin@ovz01 conf]$ sudo vzctl start service ssh                             ",{}]]},"cursor":{"x":51}}],[0.099254,{"lines":{"6":[["[oneadmin@ovz01 conf]$ sudo vzctl start service sshd                            ",{}]]},"cursor":{"x":52}}],[0.100087,{"cursor":{"x":53}}],[0.212002,{"lines":{"6":[["[oneadmin@ovz01 conf]$ sudo vzctl start service sshd s                          ",{}]]},"cursor":{"x":54}}],[0.340905,{"lines":{"6":[["[oneadmin@ovz01 conf]$ sudo vzctl start service sshd st                         ",{}]]},"cursor":{"x":55}}],[0.129921,{"lines":{"6":[["[oneadmin@ovz01 conf]$ sudo vzctl start service sshd sta                        ",{}]]},"cursor":{"x":56}}],[0.100117,{"lines":{"6":[["[oneadmin@ovz01 conf]$ sudo vzctl start service sshd stat                       ",{}]]},"cursor":{"x":57}}],[0.151128,{"lines":{"6":[["[oneadmin@ovz01 conf]$ sudo vzctl start service sshd statu                      ",{}]]},"cursor":{"x":58}}],[0.07864599999999999,{"lines":{"6":[["[oneadmin@ovz01 conf]$ sudo vzctl start service sshd status                     ",{}]]},"cursor":{"x":59}}],[0.130118,{"cursor":{"x":0,"y":7}}],[0.3511,{"lines":{"7":[["Bad CT ID service                                                               ",{}]]},"cursor":{"y":8}}],[0.011758,{"lines":{"8":[["[oneadmin@ovz01 conf]$                                                          ",{}]]},"cursor":{"x":23}}],[7.728243,{"lines":{"8":[["[oneadmin@ovz01 conf]$ sudo vzctl start service sshd status                     ",{}]]},"cursor":{"x":59}}],[0.449026,{"cursor":{"x":58}}],[0.47894,{"cursor":{"x":59}}],[1.868113,{"cursor":{"x":58}}],[0.506874,{"cursor":{"x":57}}],[0.041239,{"cursor":{"x":56}}],[0.054865,{"cursor":{"x":55}}],[0.023693,{"cursor":{"x":54}}],[0.035528,{"cursor":{"x":53}}],[0.031866,{"cursor":{"x":52}}],[0.078907,{"cursor":{"x":51}}],[0.043024,{"cursor":{"x":50}}],[0.041795,{"cursor":{"x":49}}],[0.005986,{"cursor":{"x":48}}],[0.06292300000000001,{"cursor":{"x":47}}],[0.058148,{"cursor":{"x":46}}],[0.009124,{"cursor":{"x":45}}],[0.042759,{"cursor":{"x":44}}],[0.191385,{"cursor":{"x":43}}],[0.170853,{"cursor":{"x":42}}],[0.157803,{"cursor":{"x":41}}],[0.199321,{"cursor":{"x":40}}],[0.851828,{"cursor":{"x":39}}],[0.902165,{"lines":{"8":[["[oneadmin@ovz01 conf]$ sudo vzctl star service sshd status                      ",{}]]},"cursor":{"x":38}}],[0.497724,{"lines":{"8":[["[oneadmin@ovz01 conf]$ sudo vzctl sta service sshd status                       ",{}]]},"cursor":{"x":37}}],[1.387965,{"lines":{"8":[["[oneadmin@ovz01 conf]$ sudo vzctl st service sshd status                        ",{}]]},"cursor":{"x":36}}],[0.216202,{"lines":{"8":[["[oneadmin@ovz01 conf]$ sudo vzctl s service sshd status                         ",{}]]},"cursor":{"x":35}}],[0.082941,{"lines":{"8":[["[oneadmin@ovz01 conf]$ sudo vzctl  service sshd status                          ",{}]]},"cursor":{"x":34}}],[0.150167,{"lines":{"8":[["[oneadmin@ovz01 conf]$ sudo vzctl service sshd status                           ",{}]]},"cursor":{"x":33}}],[0.137711,{"lines":{"8":[["[oneadmin@ovz01 conf]$ sudo vzct service sshd status                            ",{}]]},"cursor":{"x":32}}],[0.173325,{"lines":{"8":[["[oneadmin@ovz01 conf]$ sudo vzc service sshd status                             ",{}]]},"cursor":{"x":31}}],[0.097924,{"lines":{"8":[["[oneadmin@ovz01 conf]$ sudo vz service sshd status                              ",{}]]},"cursor":{"x":30}}],[0.13977,{"lines":{"8":[["[oneadmin@ovz01 conf]$ sudo v service sshd status                               ",{}]]},"cursor":{"x":29}}],[0.42989,{"lines":{"8":[["[oneadmin@ovz01 conf]$ sudo  service sshd status                                ",{}]]},"cursor":{"x":28}}],[0.247355,{"lines":{"8":[["[oneadmin@ovz01 conf]$ sudo e service sshd status                               ",{}]]},"cursor":{"x":29}}],[0.266074,{"lines":{"8":[["[oneadmin@ovz01 conf]$ sudo ex service sshd status                              ",{}]]},"cursor":{"x":30}}],[0.176003,{"lines":{"8":[["[oneadmin@ovz01 conf]$ sudo exe service sshd status                             ",{}]]},"cursor":{"x":31}}],[0.17958,{"lines":{"8":[["[oneadmin@ovz01 conf]$ sudo exec service sshd status                            ",{}]]},"cursor":{"x":32}}],[0.50837,{"lines":{"8":[["[oneadmin@ovz01 conf]$ sudo exec  service sshd status                           ",{}]]},"cursor":{"x":33}}],[0.196016,{"lines":{"8":[["[oneadmin@ovz01 conf]$ sudo exec 1 service sshd status                          ",{}]]},"cursor":{"x":34}}],[0.229923,{"lines":{"8":[["[oneadmin@ovz01 conf]$ sudo exec 10 service sshd status                         ",{}]]},"cursor":{"x":35}}],[0.742806,{"lines":{"8":[["[oneadmin@ovz01 conf]$ sudo exec 105 service sshd status                        ",{}]]},"cursor":{"x":36}}],[0.070116,{"lines":{"8":[["[oneadmin@ovz01 conf]$ sudo exec 105  service sshd status                       ",{}]]},"cursor":{"x":37}}],[0.193016,{"cursor":{"x":0,"y":9}}],[0.057941,{"lines":{"9":[["sudo:                                                                           ",{}]]},"cursor":{"x":6}}],[0.014044,{"lines":{"9":[["sudo: exec: command not found                                                   ",{}]],"10":[["[oneadmin@ovz01 conf]$                                                          ",{}]]},"cursor":{"x":23,"y":10}}],[2.327149,{"lines":{"10":[["[oneadmin@ovz01 conf]$ sudo exec 105  service sshd status                       ",{}]]},"cursor":{"x":57}}],[0.191965,{"cursor":{"x":56}}],[0.463756,{"cursor":{"x":55}}],[0.037051,{"cursor":{"x":54}}],[0.062107,{"cursor":{"x":53}}],[0.01504,{"cursor":{"x":52}}],[0.034051,{"cursor":{"x":51}}],[0.055957,{"cursor":{"x":50}}],[0.029853,{"cursor":{"x":49}}],[0.07398100000000001,{"cursor":{"x":48}}],[0.009065999999999999,{"cursor":{"x":47}}],[0.00779,{"cursor":{"x":46}}],[0.040161,{"cursor":{"x":45}}],[0.027991,{"cursor":{"x":44}}],[0.047156,{"cursor":{"x":43}}],[0.034718,{"cursor":{"x":42}}],[0.03325,{"cursor":{"x":41}}],[0.041141,{"cursor":{"x":40}}],[0.042682,{"cursor":{"x":39}}],[0.038041,{"cursor":{"x":38}}],[0.036998,{"cursor":{"x":37}}],[0.043074,{"cursor":{"x":36}}],[0.031006,{"cursor":{"x":35}}],[0.032189,{"cursor":{"x":34}}],[0.041494,{"cursor":{"x":33}}],[0.034141,{"cursor":{"x":32}}],[0.034057,{"cursor":{"x":31}}],[0.086159,{"cursor":{"x":30}}],[0.017142,{"cursor":{"x":29}}],[0.453925,{"cursor":{"x":28}}],[0.63285,{"lines":{"10":[["[oneadmin@ovz01 conf]$ sudo vexec 105  service sshd status                      ",{}]]},"cursor":{"x":29}}],[0.094218,{"lines":{"10":[["[oneadmin@ovz01 conf]$ sudo vzexec 105  service sshd status                     ",{}]]},"cursor":{"x":30}}],[0.185053,{"lines":{"10":[["[oneadmin@ovz01 conf]$ sudo vzcexec 105  service sshd status                    ",{}]]},"cursor":{"x":31}}],[0.450808,{"lines":{"10":[["[oneadmin@ovz01 conf]$ sudo vzctexec 105  service sshd status                   ",{}]]},"cursor":{"x":32}}],[1.434818,{"lines":{"10":[["[oneadmin@ovz01 conf]$ sudo vzctlexec 105  service sshd status                  ",{}]]},"cursor":{"x":33}}],[0.063096,{"lines":{"10":[["[oneadmin@ovz01 conf]$ sudo vzctl exec 105  service sshd status                 ",{}]]},"cursor":{"x":34}}],[0.131057,{"cursor":{"x":0,"y":11}}],[0.499004,{"lines":{"11":[["sshd (pid 452) is running...                                                    ",{}]]},"cursor":{"y":12}}],[0.020833,{}],[0.000123,{"lines":{"12":[["[oneadmin@ovz01 conf]$                                                          ",{}]]},"cursor":{"x":23}}],[14.760165,{"lines":{"12":[["[oneadmin@ovz01 conf]$ v                                                        ",{}]]},"cursor":{"x":24}}],[0.064952,{"lines":{"12":[["[oneadmin@ovz01 conf]$ vz                                                       ",{}]]},"cursor":{"x":25}}],[0.231073,{"lines":{"12":[["[oneadmin@ovz01 conf]$ vzc                                                      ",{}]]},"cursor":{"x":26}}],[0.236716,{"lines":{"12":[["[oneadmin@ovz01 conf]$ vzct                                                     ",{}]]},"cursor":{"x":27}}],[0.153906,{"lines":{"12":[["[oneadmin@ovz01 conf]$ vzctl                                                    ",{}]]},"cursor":{"x":28}}],[0.096083,{"cursor":{"x":29}}],[0.5743279999999999,{"cursor":{"x":28}}],[0.502978,{"lines":{"12":[["[oneadmin@ovz01 conf]$ vzct                                                     ",{}]]},"cursor":{"x":27}}],[0.037623,{"lines":{"12":[["[oneadmin@ovz01 conf]$ vzc                                                      ",{}]]},"cursor":{"x":26}}],[0.054264,{"lines":{"12":[["[oneadmin@ovz01 conf]$ vz                                                       ",{}]]},"cursor":{"x":25}}],[0.028662,{"lines":{"12":[["[oneadmin@ovz01 conf]$ v                                                        ",{}]]},"cursor":{"x":24}}],[0.033327,{"lines":{"12":[["[oneadmin@ovz01 conf]$                                                          ",{}]]},"cursor":{"x":23}}],[0.045105,{}],[0.064966,{}],[0.035973,{}],[0.09264600000000001,{}],[0.006328,{}],[0.232106,{"lines":{"12":[["[oneadmin@ovz01 conf]$ s                                                        ",{}]]},"cursor":{"x":24}}],[0.055747,{"lines":{"12":[["[oneadmin@ovz01 conf]$ su                                                       ",{}]]},"cursor":{"x":25}}],[0.14109,{"lines":{"12":[["[oneadmin@ovz01 conf]$ sud                                                      ",{}]]},"cursor":{"x":26}}],[0.081777,{"lines":{"12":[["[oneadmin@ovz01 conf]$ sudo                                                     ",{}]]},"cursor":{"x":27}}],[0.069215,{"cursor":{"x":28}}],[0.378881,{"lines":{"12":[["[oneadmin@ovz01 conf]$ sudo v                                                   ",{}]]},"cursor":{"x":29}}],[0.159942,{"lines":{"12":[["[oneadmin@ovz01 conf]$ sudo vz                                                  ",{}]]},"cursor":{"x":30}}],[0.444308,{"lines":{"12":[["[oneadmin@ovz01 conf]$ sudo vzs                                                 ",{}]]},"cursor":{"x":31}}],[0.278007,{"lines":{"12":[["[oneadmin@ovz01 conf]$ sudo vz                                                  ",{}]]},"cursor":{"x":30}}],[0.083357,{"lines":{"12":[["[oneadmin@ovz01 conf]$ sudo vzc                                                 ",{}]]},"cursor":{"x":31}}],[0.701785,{"lines":{"12":[["[oneadmin@ovz01 conf]$ sudo vzct                                                ",{}]]},"cursor":{"x":32}}],[0.071044,{"lines":{"12":[["[oneadmin@ovz01 conf]$ sudo vzctl                                               ",{}]]},"cursor":{"x":33}}],[0.053781,{"cursor":{"x":34}}],[0.8451650000000001,{"lines":{"12":[["[oneadmin@ovz01 conf]$ sudo vzctl s                                             ",{}]]},"cursor":{"x":35}}],[0.17962,{"lines":{"12":[["[oneadmin@ovz01 conf]$ sudo vzctl se                                            ",{}]]},"cursor":{"x":36}}],[0.147069,{"lines":{"12":[["[oneadmin@ovz01 conf]$ sudo vzctl set                                           ",{}]]},"cursor":{"x":37}}],[0.07718800000000001,{"cursor":{"x":38}}],[0.391004,{"lines":{"12":[["[oneadmin@ovz01 conf]$ sudo vzctl set 1                                         ",{}]]},"cursor":{"x":39}}],[0.310876,{"lines":{"12":[["[oneadmin@ovz01 conf]$ sudo vzctl set 10                                        ",{}]]},"cursor":{"x":40}}],[0.309093,{"lines":{"12":[["[oneadmin@ovz01 conf]$ sudo vzctl set 105                                       ",{}]]},"cursor":{"x":41}}],[1.032757,{"cursor":{"x":42}}],[0.869448,{"lines":{"12":[["[oneadmin@ovz01 conf]$ sudo vzctl set 105 -                                     ",{}]]},"cursor":{"x":43}}],[0.152697,{"lines":{"12":[["[oneadmin@ovz01 conf]$ sudo vzctl set 105 --                                    ",{}]]},"cursor":{"x":44}}],[0.545892,{"lines":{"12":[["[oneadmin@ovz01 conf]$ sudo vzctl set 105 --u                                   ",{}]]},"cursor":{"x":45}}],[0.133914,{"lines":{"12":[["[oneadmin@ovz01 conf]$ sudo vzctl set 105 --us                                  ",{}]]},"cursor":{"x":46}}],[0.184309,{"lines":{"12":[["[oneadmin@ovz01 conf]$ sudo vzctl set 105 --use                                 ",{}]]},"cursor":{"x":47}}],[0.159938,{"lines":{"12":[["[oneadmin@ovz01 conf]$ sudo vzctl set 105 --user                                ",{}]]},"cursor":{"x":48}}],[0.781508,{"lines":{"12":[["[oneadmin@ovz01 conf]$ sudo vzctl set 105 --userp                               ",{}]]},"cursor":{"x":49}}],[0.072648,{"lines":{"12":[["[oneadmin@ovz01 conf]$ sudo vzctl set 105 --userpa                              ",{}]]},"cursor":{"x":50}}],[0.215974,{"lines":{"12":[["[oneadmin@ovz01 conf]$ sudo vzctl set 105 --userpas                             ",{}]]},"cursor":{"x":51}}],[0.147857,{"lines":{"12":[["[oneadmin@ovz01 conf]$ sudo vzctl set 105 --userpass                            ",{}]]},"cursor":{"x":52}}],[0.174096,{"lines":{"12":[["[oneadmin@ovz01 conf]$ sudo vzctl set 105 --userpassw                           ",{}]]},"cursor":{"x":53}}],[0.222705,{"lines":{"12":[["[oneadmin@ovz01 conf]$ sudo vzctl set 105 --userpasswd                          ",{}]]},"cursor":{"x":54}}],[0.7984250000000001,{"cursor":{"x":55}}],[0.592761,{"lines":{"12":[["[oneadmin@ovz01 conf]$ sudo vzctl set 105 --userpasswd r                        ",{}]]},"cursor":{"x":56}}],[0.393043,{"lines":{"12":[["[oneadmin@ovz01 conf]$ sudo vzctl set 105 --userpasswd ro                       ",{}]]},"cursor":{"x":57}}],[0.145731,{"lines":{"12":[["[oneadmin@ovz01 conf]$ sudo vzctl set 105 --userpasswd roo                      ",{}]]},"cursor":{"x":58}}],[0.138186,{"lines":{"12":[["[oneadmin@ovz01 conf]$ sudo vzctl set 105 --userpasswd root                     ",{}]]},"cursor":{"x":59}}],[0.913837,{"lines":{"12":[["[oneadmin@ovz01 conf]$ sudo vzctl set 105 --userpasswd root:                    ",{}]]},"cursor":{"x":60}}],[0.77327,{"lines":{"12":[["[oneadmin@ovz01 conf]$ sudo vzctl set 105 --userpasswd root:p                   ",{}]]},"cursor":{"x":61}}],[0.052975,{"lines":{"12":[["[oneadmin@ovz01 conf]$ sudo vzctl set 105 --userpasswd root:pa                  ",{}]]},"cursor":{"x":62}}],[0.196749,{"lines":{"12":[["[oneadmin@ovz01 conf]$ sudo vzctl set 105 --userpasswd root:pas                 ",{}]]},"cursor":{"x":63}}],[0.12932,{"lines":{"12":[["[oneadmin@ovz01 conf]$ sudo vzctl set 105 --userpasswd root:pass                ",{}]]},"cursor":{"x":64}}],[0.154015,{"lines":{"12":[["[oneadmin@ovz01 conf]$ sudo vzctl set 105 --userpasswd root:passw               ",{}]]},"cursor":{"x":65}}],[0.07691099999999999,{"lines":{"12":[["[oneadmin@ovz01 conf]$ sudo vzctl set 105 --userpasswd root:passwo              ",{}]]},"cursor":{"x":66}}],[0.106798,{"lines":{"12":[["[oneadmin@ovz01 conf]$ sudo vzctl set 105 --userpasswd root:passwor             ",{}]]},"cursor":{"x":67}}],[0.191943,{"lines":{"12":[["[oneadmin@ovz01 conf]$ sudo vzctl set 105 --userpasswd root:password            ",{}]]},"cursor":{"x":68}}],[0.04211,{"cursor":{"x":0,"y":13}}],[0.433931,{"lines":{"13":[["Changing password for user root.                                                ",{}]],"14":[["passwd: all authentication tokens updated successfully.                         ",{}]]},"cursor":{"y":15}}],[0.020038,{"lines":{"15":[["[oneadmin@ovz01 conf]$                                                          ",{}]]},"cursor":{"x":23}}],[12.097192,{"lines":{"15":[["[oneadmin@ovz01 conf]$ v                                                        ",{}]]},"cursor":{"x":24}}],[0.08956500000000001,{"lines":{"15":[["[oneadmin@ovz01 conf]$ vz                                                       ",{}]]},"cursor":{"x":25}}],[0.441236,{"lines":{"15":[["[oneadmin@ovz01 conf]$ vzc                                                      ",{}]]},"cursor":{"x":26}}],[0.3032,{"lines":{"15":[["[oneadmin@ovz01 conf]$ vzct                                                     ",{}]]},"cursor":{"x":27}}],[0.07388400000000001,{"lines":{"15":[["[oneadmin@ovz01 conf]$ vzctl                                                    ",{}]]},"cursor":{"x":28}}],[0.056925,{"cursor":{"x":29}}],[0.52413,{"lines":{"15":[["[oneadmin@ovz01 conf]$ vzctl s                                                  ",{}]]},"cursor":{"x":30}}],[0.190058,{"lines":{"15":[["[oneadmin@ovz01 conf]$ vzctl st                                                 ",{}]]},"cursor":{"x":31}}],[0.107078,{"lines":{"15":[["[oneadmin@ovz01 conf]$ vzctl sta                                                ",{}]]},"cursor":{"x":32}}],[0.066971,{"lines":{"15":[["[oneadmin@ovz01 conf]$ vzctl stat                                               ",{}]]},"cursor":{"x":33}}],[0.16749,{"lines":{"15":[["[oneadmin@ovz01 conf]$ vzctl statu                                              ",{}]]},"cursor":{"x":34}}],[0.066166,{"lines":{"15":[["[oneadmin@ovz01 conf]$ vzctl status                                             ",{}]]},"cursor":{"x":35}}],[0.229279,{"cursor":{"x":36}}],[0.122833,{"lines":{"15":[["[oneadmin@ovz01 conf]$ vzctl status 1                                           ",{}]]},"cursor":{"x":37}}],[0.194084,{"lines":{"15":[["[oneadmin@ovz01 conf]$ vzctl status 10                                          ",{}]]},"cursor":{"x":38}}],[0.384961,{"lines":{"15":[["[oneadmin@ovz01 conf]$ vzctl status 105                                         ",{}]]},"cursor":{"x":39}}],[0.048953,{"cursor":{"x":0,"y":16}}],[0.194124,{"lines":{"16":[["Unable to open /dev/vzctl: Permission denied                                    ",{}]],"17":[["Please check that vzdev kernel module is loaded and you have sufficient permissi",{}]],"18":[["ons to access the file.                                                         ",{}]]},"cursor":{"y":19}}],[0.040855,{"lines":{"19":[["[oneadmin@ovz01 conf]$                                                          ",{}]]},"cursor":{"x":23}}],[1.820164,{"lines":{"19":[["[oneadmin@ovz01 conf]$ s                                                        ",{}]]},"cursor":{"x":24}}],[0.06500599999999999,{"lines":{"19":[["[oneadmin@ovz01 conf]$ su                                                       ",{}]]},"cursor":{"x":25}}],[0.204826,{"lines":{"19":[["[oneadmin@ovz01 conf]$ sud                                                      ",{}]]},"cursor":{"x":26}}],[0.015004,{"lines":{"19":[["[oneadmin@ovz01 conf]$ sudo                                                     ",{}]]},"cursor":{"x":27}}],[0.087939,{"cursor":{"x":28}}],[0.20902,{"lines":{"19":[["[oneadmin@ovz01 conf]$ sudo v                                                   ",{}]]},"cursor":{"x":29}}],[0.240168,{"lines":{"19":[["[oneadmin@ovz01 conf]$ sudo vz                                                  ",{}]]},"cursor":{"x":30}}],[0.186673,{"lines":{"19":[["[oneadmin@ovz01 conf]$ sudo vzc                                                 ",{}]]},"cursor":{"x":31}}],[0.208134,{"lines":{"19":[["[oneadmin@ovz01 conf]$ sudo vzct                                                ",{}]]},"cursor":{"x":32}}],[0.120178,{"lines":{"19":[["[oneadmin@ovz01 conf]$ sudo vzctl                                               ",{}]]},"cursor":{"x":33}}],[0.063286,{"cursor":{"x":34}}],[0.952402,{"lines":{"19":[["[oneadmin@ovz01 conf]$ sudo vzctl s                                             ",{}]]},"cursor":{"x":35}}],[0.445449,{"lines":{"19":[["[oneadmin@ovz01 conf]$ sudo vzctl st                                            ",{}]]},"cursor":{"x":36}}],[0.055787,{"lines":{"19":[["[oneadmin@ovz01 conf]$ sudo vzctl sta                                           ",{}]]},"cursor":{"x":37}}],[0.186023,{"lines":{"19":[["[oneadmin@ovz01 conf]$ sudo vzctl stat                                          ",{}]]},"cursor":{"x":38}}],[0.254157,{"lines":{"19":[["[oneadmin@ovz01 conf]$ sudo vzctl statu                                         ",{}]]},"cursor":{"x":39}}],[0.113828,{"lines":{"19":[["[oneadmin@ovz01 conf]$ sudo vzctl status                                        ",{}]]},"cursor":{"x":40}}],[0.14619,{"cursor":{"x":41}}],[0.18464,{"lines":{"19":[["[oneadmin@ovz01 conf]$ sudo vzctl status 1                                      ",{}]]},"cursor":{"x":42}}],[0.112316,{"lines":{"19":[["[oneadmin@ovz01 conf]$ sudo vzctl status 10                                     ",{}]]},"cursor":{"x":43}}],[0.645028,{"lines":{"19":[["[oneadmin@ovz01 conf]$ sudo vzctl status 105                                    ",{}]]},"cursor":{"x":44}}],[0.04187,{"cursor":{"x":0,"y":20}}],[0.124884,{"lines":{"20":[["CTID 105 exist mounted running                                                  ",{}]]},"cursor":{"y":21}}],[0.016217,{}],[0.013021,{"lines":{"21":[["[oneadmin@ovz01 conf]$                                                          ",{}]]},"cursor":{"x":23}}],[6.997988,{"lines":{"21":[["[oneadmin@ovz01 conf]$ s                                                        ",{}]]},"cursor":{"x":24}}],[0.083736,{"lines":{"21":[["[oneadmin@ovz01 conf]$ su                                                       ",{}]]},"cursor":{"x":25}}],[0.378275,{"lines":{"21":[["[oneadmin@ovz01 conf]$ sud                                                      ",{}]]},"cursor":{"x":26}}],[0.052851,{"lines":{"21":[["[oneadmin@ovz01 conf]$ sudo                                                     ",{}]]},"cursor":{"x":27}}],[0.032145,{"cursor":{"x":28}}],[0.791664,{"lines":{"21":[["[oneadmin@ovz01 conf]$ sudo v                                                   ",{}]]},"cursor":{"x":29}}],[0.095192,{"lines":{"21":[["[oneadmin@ovz01 conf]$ sudo vz                                                  ",{}]]},"cursor":{"x":30}}],[0.223062,{"lines":{"21":[["[oneadmin@ovz01 conf]$ sudo vzl                                                 ",{}]]},"cursor":{"x":31}}],[0.153901,{"lines":{"21":[["[oneadmin@ovz01 conf]$ sudo vzli                                                ",{}]]},"cursor":{"x":32}}],[0.07929600000000001,{"lines":{"21":[["[oneadmin@ovz01 conf]$ sudo vzlis                                               ",{}]]},"cursor":{"x":33}}],[0.167602,{"lines":{"21":[["[oneadmin@ovz01 conf]$ sudo vzlist                                              ",{}]]},"cursor":{"x":34}}],[0.074226,{"cursor":{"x":0,"y":22}}],[0.200921,{"lines":{"0":[["Starting container ...                                                          ",{}]],"1":[["Container is mounted                                                            ",{}]],"2":[["Adding IP address(es): 192.168.1.105                                            ",{}]],"3":[["Setting CPU units: 1000                                                         ",{}]],"4":[["Container start in progress...                                                  ",{}]],"5":[["[oneadmin@ovz01 conf]$ sudo vzctl start service sshd status                     ",{}]],"6":[["Bad CT ID service                                                               ",{}]],"7":[["[oneadmin@ovz01 conf]$ sudo exec 105  service sshd status                       ",{}]],"8":[["sudo: exec: command not found                                                   ",{}]],"9":[["[oneadmin@ovz01 conf]$ sudo vzctl exec 105  service sshd status                 ",{}]],"10":[["sshd (pid 452) is running...                                                    ",{}]],"11":[["[oneadmin@ovz01 conf]$ sudo vzctl set 105 --userpasswd root:password            ",{}]],"12":[["Changing password for user root.                                                ",{}]],"13":[["passwd: all authentication tokens updated successfully.                         ",{}]],"14":[["[oneadmin@ovz01 conf]$ vzctl status 105                                         ",{}]],"15":[["Unable to open /dev/vzctl: Permission denied                                    ",{}]],"16":[["Please check that vzdev kernel module is loaded and you have sufficient permissi",{}]],"17":[["ons to access the file.                                                         ",{}]],"18":[["[oneadmin@ovz01 conf]$ sudo vzctl status 105                                    ",{}]],"19":[["CTID 105 exist mounted running                                                  ",{}]],"20":[["[oneadmin@ovz01 conf]$ sudo vzlist                                              ",{}]],"21":[["      CTID      NPROC STATUS    IP_ADDR         HOSTNAME                        ",{}]],"22":[["       105          6 running   192.168.1.105   container105.agh.pl             ",{}]]},"cursor":{"y":23}}],[0.011828,{"lines":{"23":[["[oneadmin@ovz01 conf]$                                                          ",{}]]},"cursor":{"x":23}}],[15.075268,{"lines":{"23":[["[oneadmin@ovz01 conf]$ l                                                        ",{}]]},"cursor":{"x":24}}],[0.052843,{"lines":{"23":[["[oneadmin@ovz01 conf]$ le                                                       ",{}]]},"cursor":{"x":25}}],[0.227012,{"lines":{"23":[["[oneadmin@ovz01 conf]$ les                                                      ",{}]]},"cursor":{"x":26}}],[0.154325,{"lines":{"23":[["[oneadmin@ovz01 conf]$ less                                                     ",{}]]},"cursor":{"x":27}}],[0.056854,{"cursor":{"x":28}}],[1.024045,{"lines":{"23":[["[oneadmin@ovz01 conf]$ less /                                                   ",{}]]},"cursor":{"x":29}}],[0.192006,{"lines":{"23":[["[oneadmin@ovz01 conf]$ less /p                                                  ",{}]]},"cursor":{"x":30}}],[0.06306100000000001,{"lines":{"23":[["[oneadmin@ovz01 conf]$ less /proc/                                              ",{}]]},"cursor":{"x":34}}],[1.834968,{"lines":{"23":[["[oneadmin@ovz01 conf]$ less /proc/v                                             ",{}]]},"cursor":{"x":35}}],[0.064958,{"lines":{"23":[["[oneadmin@ovz01 conf]$ less /proc/vz                                            ",{}]]},"cursor":{"x":36}}],[0.094835,{"lines":{"23":[["[oneadmin@ovz01 conf]$ less /proc/vz/                                           ",{}]]},"cursor":{"x":37}}],[1.12984,{"lines":{"23":[["[oneadmin@ovz01 conf]$ less /proc/vz/v                                          ",{}]]},"cursor":{"x":38}}],[0.060248,{"lines":{"23":[["[oneadmin@ovz01 conf]$ less /proc/vz/vz                                         ",{}]]},"cursor":{"x":39}}],[1.081772,{"lines":{"23":[["[oneadmin@ovz01 conf]$ less /proc/vz/v                                          ",{}]]},"cursor":{"x":38}}],[0.161028,{"lines":{"23":[["[oneadmin@ovz01 conf]$ less /proc/vz/ve                                         ",{}]]},"cursor":{"x":39}}],[0.09800399999999999,{}],[0.069346,{"lines":{"23":[["[oneadmin@ovz01 conf]$ less /proc/vz/vei                                        ",{}]]},"cursor":{"x":40}}],[0.241656,{}],[0.391366,{"lines":{"0":[["Adding IP address(es): 192.168.1.105                                            ",{}]],"1":[["Setting CPU units: 1000                                                         ",{}]],"2":[["Container start in progress...                                                  ",{}]],"3":[["[oneadmin@ovz01 conf]$ sudo vzctl start service sshd status                     ",{}]],"4":[["Bad CT ID service                                                               ",{}]],"5":[["[oneadmin@ovz01 conf]$ sudo exec 105  service sshd status                       ",{}]],"6":[["sudo: exec: command not found                                                   ",{}]],"7":[["[oneadmin@ovz01 conf]$ sudo vzctl exec 105  service sshd status                 ",{}]],"8":[["sshd (pid 452) is running...                                                    ",{}]],"9":[["[oneadmin@ovz01 conf]$ sudo vzctl set 105 --userpasswd root:password            ",{}]],"10":[["Changing password for user root.                                                ",{}]],"11":[["passwd: all authentication tokens updated successfully.                         ",{}]],"12":[["[oneadmin@ovz01 conf]$ vzctl status 105                                         ",{}]],"13":[["Unable to open /dev/vzctl: Permission denied                                    ",{}]],"14":[["Please check that vzdev kernel module is loaded and you have sufficient permissi",{}]],"15":[["ons to access the file.                                                         ",{}]],"16":[["[oneadmin@ovz01 conf]$ sudo vzctl status 105                                    ",{}]],"17":[["CTID 105 exist mounted running                                                  ",{}]],"18":[["[oneadmin@ovz01 conf]$ sudo vzlist                                              ",{}]],"19":[["      CTID      NPROC STATUS    IP_ADDR         HOSTNAME                        ",{}]],"20":[["       105          6 running   192.168.1.105   container105.agh.pl             ",{}]],"21":[["[oneadmin@ovz01 conf]$ less /proc/vz/vei                                        ",{}]],"22":[["veinfo  veip                                                                    ",{}]]}}],[1.540835,{"lines":{"23":[["[oneadmin@ovz01 conf]$ less /proc/vz/vein                                       ",{}]]},"cursor":{"x":41}}],[0.044854,{"lines":{"23":[["[oneadmin@ovz01 conf]$ less /proc/vz/veinfo                                     ",{}]]},"cursor":{"x":44}}],[0.542347,{"lines":{"0":[["Setting CPU units: 1000                                                         ",{}]],"1":[["Container start in progress...                                                  ",{}]],"2":[["[oneadmin@ovz01 conf]$ sudo vzctl start service sshd status                     ",{}]],"3":[["Bad CT ID service                                                               ",{}]],"4":[["[oneadmin@ovz01 conf]$ sudo exec 105  service sshd status                       ",{}]],"5":[["sudo: exec: command not found                                                   ",{}]],"6":[["[oneadmin@ovz01 conf]$ sudo vzctl exec 105  service sshd status                 ",{}]],"7":[["sshd (pid 452) is running...                                                    ",{}]],"8":[["[oneadmin@ovz01 conf]$ sudo vzctl set 105 --userpasswd root:password            ",{}]],"9":[["Changing password for user root.                                                ",{}]],"10":[["passwd: all authentication tokens updated successfully.                         ",{}]],"11":[["[oneadmin@ovz01 conf]$ vzctl status 105                                         ",{}]],"12":[["Unable to open /dev/vzctl: Permission denied                                    ",{}]],"13":[["Please check that vzdev kernel module is loaded and you have sufficient permissi",{}]],"14":[["ons to access the file.                                                         ",{}]],"15":[["[oneadmin@ovz01 conf]$ sudo vzctl status 105                                    ",{}]],"16":[["CTID 105 exist mounted running                                                  ",{}]],"17":[["[oneadmin@ovz01 conf]$ sudo vzlist                                              ",{}]],"18":[["      CTID      NPROC STATUS    IP_ADDR         HOSTNAME                        ",{}]],"19":[["       105          6 running   192.168.1.105   container105.agh.pl             ",{}]],"20":[["[oneadmin@ovz01 conf]$ less /proc/vz/vei                                        ",{}]],"21":[["veinfo  veip                                                                    ",{}]],"22":[["[oneadmin@ovz01 conf]$ less /proc/vz/veinfo                                     ",{}]],"23":[["                                                                                ",{}]]},"cursor":{"x":0}}],[0.183867,{"lines":{"0":[["Container start in progress...                                                  ",{}]],"1":[["[oneadmin@ovz01 conf]$ sudo vzctl start service sshd status                     ",{}]],"2":[["Bad CT ID service                                                               ",{}]],"3":[["[oneadmin@ovz01 conf]$ sudo exec 105  service sshd status                       ",{}]],"4":[["sudo: exec: command not found                                                   ",{}]],"5":[["[oneadmin@ovz01 conf]$ sudo vzctl exec 105  service sshd status                 ",{}]],"6":[["sshd (pid 452) is running...                                                    ",{}]],"7":[["[oneadmin@ovz01 conf]$ sudo vzctl set 105 --userpasswd root:password            ",{}]],"8":[["Changing password for user root.                                                ",{}]],"9":[["passwd: all authentication tokens updated successfully.                         ",{}]],"10":[["[oneadmin@ovz01 conf]$ vzctl status 105                                         ",{}]],"11":[["Unable to open /dev/vzctl: Permission denied                                    ",{}]],"12":[["Please check that vzdev kernel module is loaded and you have sufficient permissi",{}]],"13":[["ons to access the file.                                                         ",{}]],"14":[["[oneadmin@ovz01 conf]$ sudo vzctl status 105                                    ",{}]],"15":[["CTID 105 exist mounted running                                                  ",{}]],"16":[["[oneadmin@ovz01 conf]$ sudo vzlist                                              ",{}]],"17":[["      CTID      NPROC STATUS    IP_ADDR         HOSTNAME                        ",{}]],"18":[["       105          6 running   192.168.1.105   container105.agh.pl             ",{}]],"19":[["[oneadmin@ovz01 conf]$ less /proc/vz/vei                                        ",{}]],"20":[["veinfo  veip                                                                    ",{}]],"21":[["[oneadmin@ovz01 conf]$ less /proc/vz/veinfo                                     ",{}]],"22":[["/proc/vz/veinfo: Permission denied                                              ",{}]]}}],[0.008902,{"lines":{"23":[["[oneadmin@ovz01 conf]$                                                          ",{}]]},"cursor":{"x":23}}],[1.738906,{}],[0.424191,{"lines":{"23":[["[oneadmin@ovz01 conf]$ less /proc/vz/veinfo                                     ",{}]]},"cursor":{"x":44}}],[0.095042,{"cursor":{"x":43}}],[0.473813,{"cursor":{"x":42}}],[0.05386,{"cursor":{"x":41}}],[0.028094,{"cursor":{"x":40}}],[0.053997,{"cursor":{"x":39}}],[0.019911,{"cursor":{"x":38}}],[0.047384,{"cursor":{"x":37}}],[0.05574,{"cursor":{"x":36}}],[0.014751,{"cursor":{"x":35}}],[0.049268,{"cursor":{"x":34}}],[0.031985,{"cursor":{"x":33}}],[0.113508,{"cursor":{"x":32}}],[0.047223,{"cursor":{"x":30}}],[0.056381,{"cursor":{"x":29}}],[0.011102,{"cursor":{"x":28}}],[0.141716,{"cursor":{"x":27}}],[0.037124,{"cursor":{"x":26}}],[0.025052,{"cursor":{"x":25}}],[0.025774,{"cursor":{"x":24}}],[0.043149,{"cursor":{"x":23}}],[0.048799,{}],[0.020281,{}],[0.050786,{}],[0.05829,{}],[0.040887,{}],[0.006765,{}],[0.041152,{}],[0.046318,{}],[0.298809,{"lines":{"23":[["[oneadmin@ovz01 conf]$ sless /proc/vz/veinfo                                    ",{}]]},"cursor":{"x":24}}],[0.146123,{"lines":{"23":[["[oneadmin@ovz01 conf]$ suless /proc/vz/veinfo                                   ",{}]]},"cursor":{"x":25}}],[0.057845,{"lines":{"23":[["[oneadmin@ovz01 conf]$ sudless /proc/vz/veinfo                                  ",{}]]},"cursor":{"x":26}}],[0.136836,{"lines":{"23":[["[oneadmin@ovz01 conf]$ sudoless /proc/vz/veinfo                                 ",{}]]},"cursor":{"x":27}}],[0.02402,{"lines":{"23":[["[oneadmin@ovz01 conf]$ sudo less /proc/vz/veinfo                                ",{}]]},"cursor":{"x":28}}],[0.134121,{"lines":{"0":[["[oneadmin@ovz01 conf]$ sudo vzctl start service sshd status                     ",{}]],"1":[["Bad CT ID service                                                               ",{}]],"2":[["[oneadmin@ovz01 conf]$ sudo exec 105  service sshd status                       ",{}]],"3":[["sudo: exec: command not found                                                   ",{}]],"4":[["[oneadmin@ovz01 conf]$ sudo vzctl exec 105  service sshd status                 ",{}]],"5":[["sshd (pid 452) is running...                                                    ",{}]],"6":[["[oneadmin@ovz01 conf]$ sudo vzctl set 105 --userpasswd root:password            ",{}]],"7":[["Changing password for user root.                                                ",{}]],"8":[["passwd: all authentication tokens updated successfully.                         ",{}]],"9":[["[oneadmin@ovz01 conf]$ vzctl status 105                                         ",{}]],"10":[["Unable to open /dev/vzctl: Permission denied                                    ",{}]],"11":[["Please check that vzdev kernel module is loaded and you have sufficient permissi",{}]],"12":[["ons to access the file.                                                         ",{}]],"13":[["[oneadmin@ovz01 conf]$ sudo vzctl status 105                                    ",{}]],"14":[["CTID 105 exist mounted running                                                  ",{}]],"15":[["[oneadmin@ovz01 conf]$ sudo vzlist                                              ",{}]],"16":[["      CTID      NPROC STATUS    IP_ADDR         HOSTNAME                        ",{}]],"17":[["       105          6 running   192.168.1.105   container105.agh.pl             ",{}]],"18":[["[oneadmin@ovz01 conf]$ less /proc/vz/vei                                        ",{}]],"19":[["veinfo  veip                                                                    ",{}]],"20":[["[oneadmin@ovz01 conf]$ less /proc/vz/veinfo                                     ",{}]],"21":[["/proc/vz/veinfo: Permission denied                                              ",{}]],"22":[["[oneadmin@ovz01 conf]$ sudo less /proc/vz/veinfo                                ",{}]],"23":[["                                                                                ",{}]]},"cursor":{"x":0}}],[0.309066,{"lines":{"0":[["                                                                                ",{}]],"1":[["                                                                                ",{}]],"2":[["                                                                                ",{}]],"3":[["                                                                                ",{}]],"4":[["                                                                                ",{}]],"5":[["                                                                                ",{}]],"6":[["                                                                                ",{}]],"7":[["                                                                                ",{}]],"8":[["                                                                                ",{}]],"9":[["                                                                                ",{}]],"10":[["                                                                                ",{}]],"11":[["                                                                                ",{}]],"12":[["                                                                                ",{}]],"13":[["                                                                                ",{}]],"14":[["                                                                                ",{}]],"15":[["                                                                                ",{}]],"16":[["                                                                                ",{}]],"17":[["                                                                                ",{}]],"18":[["                                                                                ",{}]],"19":[["                                                                                ",{}]],"20":[["                                                                                ",{}]],"21":[["       105     0     6   192.168.1.105                                          ",{}]],"22":[["         0     0   263                                                          ",{}]],"23":[["/proc/vz/veinfo (END) ",{"inverse":true}],["                                                          ",{}]]},"cursor":{"x":22}}],[2.174865,{"lines":{"0":[["[oneadmin@ovz01 conf]$ sudo vzctl start service sshd status                     ",{}]],"1":[["Bad CT ID service                                                               ",{}]],"2":[["[oneadmin@ovz01 conf]$ sudo exec 105  service sshd status                       ",{}]],"3":[["sudo: exec: command not found                                                   ",{}]],"4":[["[oneadmin@ovz01 conf]$ sudo vzctl exec 105  service sshd status                 ",{}]],"5":[["sshd (pid 452) is running...                                                    ",{}]],"6":[["[oneadmin@ovz01 conf]$ sudo vzctl set 105 --userpasswd root:password            ",{}]],"7":[["Changing password for user root.                                                ",{}]],"8":[["passwd: all authentication tokens updated successfully.                         ",{}]],"9":[["[oneadmin@ovz01 conf]$ vzctl status 105                                         ",{}]],"10":[["Unable to open /dev/vzctl: Permission denied                                    ",{}]],"11":[["Please check that vzdev kernel module is loaded and you have sufficient permissi",{}]],"12":[["ons to access the file.                                                         ",{}]],"13":[["[oneadmin@ovz01 conf]$ sudo vzctl status 105                                    ",{}]],"14":[["CTID 105 exist mounted running                                                  ",{}]],"15":[["[oneadmin@ovz01 conf]$ sudo vzlist                                              ",{}]],"16":[["      CTID      NPROC STATUS    IP_ADDR         HOSTNAME                        ",{}]],"17":[["       105          6 running   192.168.1.105   container105.agh.pl             ",{}]],"18":[["[oneadmin@ovz01 conf]$ less /proc/vz/vei                                        ",{}]],"19":[["veinfo  veip                                                                    ",{}]],"20":[["[oneadmin@ovz01 conf]$ less /proc/vz/veinfo                                     ",{}]],"21":[["/proc/vz/veinfo: Permission denied                                              ",{}]],"22":[["[oneadmin@ovz01 conf]$ sudo less /proc/vz/veinfo                                ",{}]],"23":[["                                                                                ",{}]]},"cursor":{"x":0}}],[0.042954,{"lines":{"23":[["[oneadmin@ovz01 conf]$                                                          ",{}]]},"cursor":{"x":23}}],[590.414227,{"lines":{"23":[["[oneadmin@ovz01 conf]$ s                                                        ",{}]]},"cursor":{"x":24}}],[0.073134,{"lines":{"23":[["[oneadmin@ovz01 conf]$ su                                                       ",{}]]},"cursor":{"x":25}}],[0.142914,{"lines":{"23":[["[oneadmin@ovz01 conf]$ sud                                                      ",{}]]},"cursor":{"x":26}}],[0.050909,{"lines":{"23":[["[oneadmin@ovz01 conf]$ sudo                                                     ",{}]]},"cursor":{"x":27}}],[0.101919,{"cursor":{"x":28}}],[0.227971,{"lines":{"23":[["[oneadmin@ovz01 conf]$ sudo v                                                   ",{}]]},"cursor":{"x":29}}],[0.210244,{"lines":{"23":[["[oneadmin@ovz01 conf]$ sudo vz                                                  ",{}]]},"cursor":{"x":30}}],[0.236803,{"lines":{"23":[["[oneadmin@ovz01 conf]$ sudo vzl                                                 ",{}]]},"cursor":{"x":31}}],[0.163006,{"lines":{"23":[["[oneadmin@ovz01 conf]$ sudo vzli                                                ",{}]]},"cursor":{"x":32}}],[0.079873,{"lines":{"23":[["[oneadmin@ovz01 conf]$ sudo vzlis                                               ",{}]]},"cursor":{"x":33}}],[0.195207,{"lines":{"23":[["[oneadmin@ovz01 conf]$ sudo vzlist                                              ",{}]]},"cursor":{"x":34}}],[0.13501,{"cursor":{"x":35}}],[0.267723,{"lines":{"23":[["[oneadmin@ovz01 conf]$ sudo vzlist -                                            ",{}]]},"cursor":{"x":36}}],[0.117983,{"lines":{"23":[["[oneadmin@ovz01 conf]$ sudo vzlist -a                                           ",{}]]},"cursor":{"x":37}}],[0.093282,{"lines":{"0":[["Bad CT ID service                                                               ",{}]],"1":[["[oneadmin@ovz01 conf]$ sudo exec 105  service sshd status                       ",{}]],"2":[["sudo: exec: command not found                                                   ",{}]],"3":[["[oneadmin@ovz01 conf]$ sudo vzctl exec 105  service sshd status                 ",{}]],"4":[["sshd (pid 452) is running...                                                    ",{}]],"5":[["[oneadmin@ovz01 conf]$ sudo vzctl set 105 --userpasswd root:password            ",{}]],"6":[["Changing password for user root.                                                ",{}]],"7":[["passwd: all authentication tokens updated successfully.                         ",{}]],"8":[["[oneadmin@ovz01 conf]$ vzctl status 105                                         ",{}]],"9":[["Unable to open /dev/vzctl: Permission denied                                    ",{}]],"10":[["Please check that vzdev kernel module is loaded and you have sufficient permissi",{}]],"11":[["ons to access the file.                                                         ",{}]],"12":[["[oneadmin@ovz01 conf]$ sudo vzctl status 105                                    ",{}]],"13":[["CTID 105 exist mounted running                                                  ",{}]],"14":[["[oneadmin@ovz01 conf]$ sudo vzlist                                              ",{}]],"15":[["      CTID      NPROC STATUS    IP_ADDR         HOSTNAME                        ",{}]],"16":[["       105          6 running   192.168.1.105   container105.agh.pl             ",{}]],"17":[["[oneadmin@ovz01 conf]$ less /proc/vz/vei                                        ",{}]],"18":[["veinfo  veip                                                                    ",{}]],"19":[["[oneadmin@ovz01 conf]$ less /proc/vz/veinfo                                     ",{}]],"20":[["/proc/vz/veinfo: Permission denied                                              ",{}]],"21":[["[oneadmin@ovz01 conf]$ sudo less /proc/vz/veinfo                                ",{}]],"22":[["[oneadmin@ovz01 conf]$ sudo vzlist -a                                           ",{}]],"23":[["                                                                                ",{}]]},"cursor":{"x":0}}],[0.340546,{"lines":{"0":[["passwd: all authentication tokens updated successfully.                         ",{}]],"1":[["[oneadmin@ovz01 conf]$ vzctl status 105                                         ",{}]],"2":[["Unable to open /dev/vzctl: Permission denied                                    ",{}]],"3":[["Please check that vzdev kernel module is loaded and you have sufficient permissi",{}]],"4":[["ons to access the file.                                                         ",{}]],"5":[["[oneadmin@ovz01 conf]$ sudo vzctl status 105                                    ",{}]],"6":[["CTID 105 exist mounted running                                                  ",{}]],"7":[["[oneadmin@ovz01 conf]$ sudo vzlist                                              ",{}]],"8":[["      CTID      NPROC STATUS    IP_ADDR         HOSTNAME                        ",{}]],"9":[["       105          6 running   192.168.1.105   container105.agh.pl             ",{}]],"10":[["[oneadmin@ovz01 conf]$ less /proc/vz/vei                                        ",{}]],"11":[["veinfo  veip                                                                    ",{}]],"12":[["[oneadmin@ovz01 conf]$ less /proc/vz/veinfo                                     ",{}]],"13":[["/proc/vz/veinfo: Permission denied                                              ",{}]],"14":[["[oneadmin@ovz01 conf]$ sudo less /proc/vz/veinfo                                ",{}]],"15":[["[oneadmin@ovz01 conf]$ sudo vzlist -a                                           ",{}]],"16":[["Unable to open /etc/vz/conf/100.conf: No such file or directory                 ",{}]],"17":[["Unable to open /etc/vz/conf/102.conf: No such file or directory                 ",{}]],"18":[["Unable to open /etc/vz/conf/103.conf: No such file or directory                 ",{}]],"19":[["      CTID      NPROC STATUS    IP_ADDR         HOSTNAME                        ",{}]],"20":[["       101          - stopped   192.168.0.100   -                               ",{}]],"21":[["       104          - stopped   192.168.0.6     -                               ",{}]],"22":[["       105          6 running   192.168.1.105   container105.agh.pl             ",{}]]}}],[0.008423,{"lines":{"23":[["[oneadmin@ovz01 conf]$                                                          ",{}]]},"cursor":{"x":23}}],[153.774963,{"lines":{"23":[["[oneadmin@ovz01 conf]$ e                                                        ",{}]]},"cursor":{"x":24}}],[0.318782,{"lines":{"23":[["[oneadmin@ovz01 conf]$ ex                                                       ",{}]]},"cursor":{"x":25}}],[0.068302,{"lines":{"23":[["[oneadmin@ovz01 conf]$ exi                                                      ",{}]]},"cursor":{"x":26}}],[0.153834,{"lines":{"23":[["[oneadmin@ovz01 conf]$ exit                                                     ",{}]]},"cursor":{"x":27}}],[0.706975,{"lines":{"0":[["Unable to open /dev/vzctl: Permission denied                                    ",{}]],"1":[["Please check that vzdev kernel module is loaded and you have sufficient permissi",{}]],"2":[["ons to access the file.                                                         ",{}]],"3":[["[oneadmin@ovz01 conf]$ sudo vzctl status 105                                    ",{}]],"4":[["CTID 105 exist mounted running                                                  ",{}]],"5":[["[oneadmin@ovz01 conf]$ sudo vzlist                                              ",{}]],"6":[["      CTID      NPROC STATUS    IP_ADDR         HOSTNAME                        ",{}]],"7":[["       105          6 running   192.168.1.105   container105.agh.pl             ",{}]],"8":[["[oneadmin@ovz01 conf]$ less /proc/vz/vei                                        ",{}]],"9":[["veinfo  veip                                                                    ",{}]],"10":[["[oneadmin@ovz01 conf]$ less /proc/vz/veinfo                                     ",{}]],"11":[["/proc/vz/veinfo: Permission denied                                              ",{}]],"12":[["[oneadmin@ovz01 conf]$ sudo less /proc/vz/veinfo                                ",{}]],"13":[["[oneadmin@ovz01 conf]$ sudo vzlist -a                                           ",{}]],"14":[["Unable to open /etc/vz/conf/100.conf: No such file or directory                 ",{}]],"15":[["Unable to open /etc/vz/conf/102.conf: No such file or directory                 ",{}]],"16":[["Unable to open /etc/vz/conf/103.conf: No such file or directory                 ",{}]],"17":[["      CTID      NPROC STATUS    IP_ADDR         HOSTNAME                        ",{}]],"18":[["       101          - stopped   192.168.0.100   -                               ",{}]],"19":[["       104          - stopped   192.168.0.6     -                               ",{}]],"20":[["       105          6 running   192.168.1.105   container105.agh.pl             ",{}]],"21":[["[oneadmin@ovz01 conf]$ exit                                                     ",{}]],"22":[["exit                                                                            ",{}]],"23":[["                                                                                ",{}]]},"cursor":{"x":0}}]]